dlk/__init__.py
dlk/cli.py
dlk/dlkParse.py
docu_lite_kit-0.3.0.dist-info/licenses/LICENSE
docu_lite_kit-0.3.0.dist-info/METADATA
docu_lite_kit-0.3.0.dist-info/WHEEL
docu_lite_kit-0.3.0.dist-info/entry_points.txt
docu_lite_kit-0.3.0.dist-info/top_level.txt
docu_lite_kit-0.3.0.dist-info/RECORD
