Metadata-Version: 2.4
Name: docu-lite-kit
Version: 0.3.0
Summary: 🧾 docu-lite-kit: Ultra-light cli/importable Python code parser tools
Author-email: G1OJS <g1ojs@yahoo.com>
License-Expression: MIT
Project-URL: Homepage, https://github.com/G1OJS/docu-lite-kit
Project-URL: Issues, https://github.com/G1OJS/docu-lite-kit/issues
Keywords: documentation,docstring,python,html,code-outline,doc-generator,lightweight,static,cli,developer-tools
Classifier: Environment :: Console
Classifier: Intended Audience :: Developers
Classifier: Programming Language :: Python :: 3
Classifier: Topic :: Documentation
Classifier: Topic :: Software Development :: Documentation
Classifier: Topic :: Software Development :: Version Control :: Git
Classifier: Topic :: Utilities
Requires-Python: >=3.8
License-File: LICENSE
Dynamic: license-file
